{
  "meta": {
    "version": "2026-05-27",
    "startDate": "2026-05-22",
    "examDate": "2026-07-22",
    "targetScore": 387,
    "level": "TEPS 2급 (중급)",
    "totalDays": 6,
    "totalWords": 164
  },
  "days": [
    {
      "day": 1,
      "date": "2026-05-22",
      "category": "vocab",
      "words": [
        {"id":"d01-01","w":"abolish","ipa":"/əˈbɒlɪʃ/","pos":"v","ko":"폐지하다","syn":["eliminate","abrogate"],"ex":"The government decided to abolish the outdated law.","exKo":"정부는 시대에 뒤진 법을 폐지하기로 결정했다."},
        {"id":"d01-02","w":"abundant","ipa":"/əˈbʌndənt/","pos":"a","ko":"풍부한","syn":["plentiful","ample"],"ex":"The region has abundant natural resources.","exKo":"그 지역에는 천연자원이 풍부하다."},
        {"id":"d01-03","w":"adversity","ipa":"/ədˈvɜːrsəti/","pos":"n","ko":"역경, 고난","syn":["hardship","misfortune"],"ex":"She showed great courage in the face of adversity.","exKo":"그녀는 역경에 맞서 큰 용기를 보여주었다."},
        {"id":"d01-04","w":"ambiguous","ipa":"/æmˈbɪɡjuəs/","pos":"a","ko":"모호한","syn":["vague","unclear"],"ex":"His answer was ambiguous and confusing.","exKo":"그의 대답은 모호하고 혼란스러웠다."},
        {"id":"d01-05","w":"apparent","ipa":"/əˈpærənt/","pos":"a","ko":"명백한, 외관상의","syn":["evident","obvious"],"ex":"It was apparent that he was lying.","exKo":"그가 거짓말하고 있다는 것은 명백했다."},
        {"id":"d01-06","w":"assess","ipa":"/əˈses/","pos":"v","ko":"평가하다","syn":["evaluate","appraise"],"ex":"We need to assess the damage caused by the storm.","exKo":"우리는 폭풍이 끼친 피해를 평가해야 한다."},
        {"id":"d01-07","w":"attain","ipa":"/əˈteɪn/","pos":"v","ko":"달성하다","syn":["achieve","accomplish"],"ex":"He worked hard to attain his goals.","exKo":"그는 목표를 달성하기 위해 열심히 일했다."},
        {"id":"d01-08","w":"authentic","ipa":"/ɔːˈθentɪk/","pos":"a","ko":"진짜의","syn":["genuine","real"],"ex":"This restaurant serves authentic Italian food.","exKo":"이 식당은 정통 이탈리아 음식을 제공한다."},
        {"id":"d01-09","w":"beneficial","ipa":"/ˌbenɪˈfɪʃəl/","pos":"a","ko":"유익한","syn":["advantageous","helpful"],"ex":"Exercise is beneficial to your health.","exKo":"운동은 건강에 유익하다."},
        {"id":"d01-10","w":"compel","ipa":"/kəmˈpel/","pos":"v","ko":"강요하다","syn":["force","oblige"],"ex":"Illness compelled him to retire early.","exKo":"병으로 인해 그는 일찍 은퇴해야 했다."},
        {"id":"d01-11","w":"contradict","ipa":"/ˌkɒntrəˈdɪkt/","pos":"v","ko":"반박하다","syn":["deny","refute"],"ex":"His actions contradict his words.","exKo":"그의 행동은 말과 모순된다."},
        {"id":"d01-12","w":"crucial","ipa":"/ˈkruːʃəl/","pos":"a","ko":"결정적인","syn":["critical","vital"],"ex":"Sleep is crucial for good health.","exKo":"잠은 건강에 결정적으로 중요하다."},
        {"id":"d01-13","w":"deteriorate","ipa":"/dɪˈtɪəriəreɪt/","pos":"v","ko":"악화되다","syn":["worsen","decline"],"ex":"His condition began to deteriorate rapidly.","exKo":"그의 상태가 급속히 악화되기 시작했다."},
        {"id":"d01-14","w":"diligent","ipa":"/ˈdɪlɪdʒənt/","pos":"a","ko":"근면한","syn":["hardworking","industrious"],"ex":"She is a diligent student who never misses class.","exKo":"그녀는 결석을 하지 않는 근면한 학생이다."},
        {"id":"d01-15","w":"distinct","ipa":"/dɪˈstɪŋkt/","pos":"a","ko":"뚜렷한","syn":["clear","separate"],"ex":"There is a distinct difference between the two.","exKo":"둘 사이에 뚜렷한 차이가 있다."},
        {"id":"d01-16","w":"elaborate","ipa":"/ɪˈlæbərət/","pos":"a","ko":"정교한, 공들인","syn":["detailed","intricate"],"ex":"She wore an elaborate costume to the party.","exKo":"그녀는 파티에 정교한 의상을 입고 갔다."},
        {"id":"d01-17","w":"eliminate","ipa":"/ɪˈlɪmɪneɪt/","pos":"v","ko":"제거하다","syn":["remove","eradicate"],"ex":"We must eliminate all errors from the report.","exKo":"보고서에서 모든 오류를 제거해야 한다."},
        {"id":"d01-18","w":"enhance","ipa":"/ɪnˈhæns/","pos":"v","ko":"향상시키다","syn":["improve","boost"],"ex":"The new feature will enhance user experience.","exKo":"새 기능은 사용자 경험을 향상시킬 것이다."},
        {"id":"d01-19","w":"evident","ipa":"/ˈevɪdənt/","pos":"a","ko":"분명한","syn":["clear","apparent"],"ex":"It was evident that she was upset.","exKo":"그녀가 화났다는 것이 분명했다."},
        {"id":"d01-20","w":"exaggerate","ipa":"/ɪɡˈzædʒəreɪt/","pos":"v","ko":"과장하다","syn":["overstate","magnify"],"ex":"Don't exaggerate the problem.","exKo":"문제를 과장하지 마라."},
        {"id":"d01-21","w":"feasible","ipa":"/ˈfiːzəbəl/","pos":"a","ko":"실현 가능한","syn":["possible","viable"],"ex":"Is the plan feasible within our budget?","exKo":"그 계획이 우리 예산 내에서 실현 가능한가?"},
        {"id":"d01-22","w":"genuine","ipa":"/ˈdʒenjuɪn/","pos":"a","ko":"진짜의, 진심의","syn":["authentic","real"],"ex":"Her smile was warm and genuine.","exKo":"그녀의 미소는 따뜻하고 진심이었다."},
        {"id":"d01-23","w":"hinder","ipa":"/ˈhɪndər/","pos":"v","ko":"방해하다","syn":["obstruct","impede"],"ex":"Bad weather hindered our progress.","exKo":"악천후가 우리의 진행을 방해했다."},
        {"id":"d01-24","w":"imminent","ipa":"/ˈɪmɪnənt/","pos":"a","ko":"임박한","syn":["impending","looming"],"ex":"An imminent storm forced us to cancel the trip.","exKo":"임박한 폭풍 때문에 여행을 취소해야 했다."},
        {"id":"d01-25","w":"inevitable","ipa":"/ɪnˈevɪtəbəl/","pos":"a","ko":"불가피한","syn":["unavoidable","certain"],"ex":"Change is inevitable in life.","exKo":"삶에서 변화는 불가피하다."}
      ]
    },
    {
      "day": 2,
      "date": "2026-05-23",
      "category": "vocab",
      "words": [
        {"id":"d02-01","w":"abide","ipa":"/əˈbaɪd/","pos":"v","ko":"견디다, 준수하다","syn":["endure","tolerate"],"ex":"I can't abide his constant complaints.","exKo":"나는 그의 끊임없는 불평을 견딜 수 없다."},
        {"id":"d02-02","w":"abrupt","ipa":"/əˈbrʌpt/","pos":"a","ko":"갑작스러운","syn":["sudden","unexpected"],"ex":"The meeting came to an abrupt end.","exKo":"회의는 갑작스럽게 끝났다."},
        {"id":"d02-03","w":"accommodate","ipa":"/əˈkɒmədeɪt/","pos":"v","ko":"수용하다","syn":["house","fit"],"ex":"The hotel can accommodate up to 500 guests.","exKo":"그 호텔은 최대 500명의 손님을 수용할 수 있다."},
        {"id":"d02-04","w":"accountable","ipa":"/əˈkaʊntəbəl/","pos":"a","ko":"책임이 있는","syn":["responsible","liable"],"ex":"Managers are accountable for their team's performance.","exKo":"관리자는 팀의 성과에 대해 책임이 있다."},
        {"id":"d02-05","w":"adept","ipa":"/əˈdept/","pos":"a","ko":"능숙한","syn":["skilled","proficient"],"ex":"She is adept at solving complex problems.","exKo":"그녀는 복잡한 문제를 해결하는 데 능숙하다."},
        {"id":"d02-06","w":"adjacent","ipa":"/əˈdʒeɪsənt/","pos":"a","ko":"인접한","syn":["neighboring","adjoining"],"ex":"My office is adjacent to the meeting room.","exKo":"내 사무실은 회의실에 인접해 있다."},
        {"id":"d02-07","w":"administer","ipa":"/ədˈmɪnɪstər/","pos":"v","ko":"관리하다, 투여하다","syn":["manage","oversee"],"ex":"She administers the company's finances.","exKo":"그녀는 회사의 재정을 관리한다."},
        {"id":"d02-08","w":"adopt","ipa":"/əˈdɒpt/","pos":"v","ko":"채택하다","syn":["embrace","take up"],"ex":"The committee adopted the new policy unanimously.","exKo":"위원회는 만장일치로 새 정책을 채택했다."},
        {"id":"d02-09","w":"affluent","ipa":"/ˈæfluənt/","pos":"a","ko":"부유한","syn":["wealthy","prosperous"],"ex":"They live in an affluent neighborhood.","exKo":"그들은 부유한 동네에 산다."},
        {"id":"d02-10","w":"agile","ipa":"/ˈædʒəl/","pos":"a","ko":"민첩한","syn":["nimble","swift"],"ex":"The agile athlete dodged every obstacle.","exKo":"민첩한 그 운동선수는 모든 장애물을 피했다."},
        {"id":"d02-11","w":"alliance","ipa":"/əˈlaɪəns/","pos":"n","ko":"동맹","syn":["coalition","partnership"],"ex":"The two companies formed a strategic alliance.","exKo":"두 회사는 전략적 동맹을 맺었다."},
        {"id":"d02-12","w":"alter","ipa":"/ˈɔːltər/","pos":"v","ko":"변경하다","syn":["change","modify"],"ex":"We need to alter the design slightly.","exKo":"우리는 디자인을 약간 변경해야 한다."},
        {"id":"d02-13","w":"anonymous","ipa":"/əˈnɒnɪməs/","pos":"a","ko":"익명의","syn":["unnamed","unidentified"],"ex":"The donor wished to remain anonymous.","exKo":"기부자는 익명을 유지하기를 원했다."},
        {"id":"d02-14","w":"appoint","ipa":"/əˈpɔɪnt/","pos":"v","ko":"임명하다","syn":["designate","nominate"],"ex":"She was appointed as the new CEO last month.","exKo":"그녀는 지난달 새 CEO로 임명되었다."},
        {"id":"d02-15","w":"appraise","ipa":"/əˈpreɪz/","pos":"v","ko":"평가하다","syn":["assess","evaluate"],"ex":"An expert was hired to appraise the painting.","exKo":"그림을 평가하기 위해 전문가가 고용되었다."},
        {"id":"d02-16","w":"ascertain","ipa":"/ˌæsərˈteɪn/","pos":"v","ko":"확인하다","syn":["determine","verify"],"ex":"We must ascertain the cause of the problem.","exKo":"우리는 문제의 원인을 확인해야 한다."},
        {"id":"d02-17","w":"assemble","ipa":"/əˈsembəl/","pos":"v","ko":"모으다, 조립하다","syn":["gather","construct"],"ex":"The students assembled in the auditorium.","exKo":"학생들이 강당에 모였다."},
        {"id":"d02-18","w":"astonish","ipa":"/əˈstɒnɪʃ/","pos":"v","ko":"놀라게 하다","syn":["amaze","astound"],"ex":"His talent astonished everyone in the room.","exKo":"그의 재능은 방 안의 모든 사람을 놀라게 했다."},
        {"id":"d02-19","w":"augment","ipa":"/ɔːɡˈment/","pos":"v","ko":"증대시키다","syn":["increase","expand"],"ex":"She took a second job to augment her income.","exKo":"그녀는 수입을 늘리기 위해 두 번째 일을 했다."},
        {"id":"d02-20","w":"avenge","ipa":"/əˈvendʒ/","pos":"v","ko":"복수하다","syn":["revenge","retaliate"],"ex":"He vowed to avenge his brother's death.","exKo":"그는 형의 죽음에 복수하겠다고 맹세했다."},
        {"id":"d02-21","w":"avid","ipa":"/ˈævɪd/","pos":"a","ko":"열렬한","syn":["keen","enthusiastic"],"ex":"She is an avid reader of mystery novels.","exKo":"그녀는 추리 소설을 열렬히 읽는 사람이다."},
        {"id":"d02-22","w":"bewilder","ipa":"/bɪˈwɪldər/","pos":"v","ko":"당황하게 하다","syn":["confuse","perplex"],"ex":"The complex instructions bewildered the students.","exKo":"복잡한 지시 사항이 학생들을 당황하게 했다."},
        {"id":"d02-23","w":"bland","ipa":"/blænd/","pos":"a","ko":"무미건조한","syn":["dull","tasteless"],"ex":"The soup tasted bland without spices.","exKo":"향신료가 없어서 수프는 무미건조한 맛이 났다."},
        {"id":"d02-24","w":"bleak","ipa":"/bliːk/","pos":"a","ko":"황량한, 암울한","syn":["gloomy","desolate"],"ex":"The future of the company looks bleak.","exKo":"회사의 미래는 암울해 보인다."},
        {"id":"d02-25","w":"brittle","ipa":"/ˈbrɪtəl/","pos":"a","ko":"부서지기 쉬운","syn":["fragile","delicate"],"ex":"Old bones become brittle and easy to break.","exKo":"늙은 뼈는 부서지기 쉬워진다."}
      ]
    },
    {
      "day": 3,
      "date": "2026-05-24",
      "category": "vocab",
      "words": [
        {"id":"d03-01","w":"abate","ipa":"/əˈbeɪt/","pos":"v","ko":"약해지다, 감소하다","syn":["lessen","subside"],"ex":"The storm finally began to abate after midnight.","exKo":"폭풍은 자정이 지나서야 마침내 약해지기 시작했다."},
        {"id":"d03-02","w":"abstain","ipa":"/əbˈsteɪn/","pos":"v","ko":"삼가다, 기권하다","syn":["refrain","forgo"],"ex":"He decided to abstain from alcohol for a month.","exKo":"그는 한 달간 술을 삼가기로 결심했다."},
        {"id":"d03-03","w":"absurd","ipa":"/əbˈsɜːrd/","pos":"a","ko":"터무니없는","syn":["ridiculous","ludicrous"],"ex":"His excuse for being late was absolutely absurd.","exKo":"그가 늦은 변명은 정말 터무니없었다."},
        {"id":"d03-04","w":"accelerate","ipa":"/əkˈseləreɪt/","pos":"v","ko":"가속하다","syn":["hasten","quicken"],"ex":"The new policy will accelerate economic growth.","exKo":"새 정책은 경제 성장을 가속화할 것이다."},
        {"id":"d03-05","w":"accessible","ipa":"/əkˈsesəbəl/","pos":"a","ko":"접근 가능한","syn":["reachable","available"],"ex":"The museum is easily accessible by subway.","exKo":"그 박물관은 지하철로 쉽게 접근할 수 있다."},
        {"id":"d03-06","w":"acclaim","ipa":"/əˈkleɪm/","pos":"v","ko":"찬사를 보내다","syn":["praise","applaud"],"ex":"Critics acclaimed her latest novel as a masterpiece.","exKo":"평론가들은 그녀의 최신 소설을 걸작이라 찬사했다."},
        {"id":"d03-07","w":"accomplice","ipa":"/əˈkɒmplɪs/","pos":"n","ko":"공범","syn":["accessory","partner"],"ex":"The thief was caught along with his accomplice.","exKo":"그 도둑은 공범과 함께 붙잡혔다."},
        {"id":"d03-08","w":"acute","ipa":"/əˈkjuːt/","pos":"a","ko":"예리한, 격심한","syn":["sharp","severe"],"ex":"Dogs have an acute sense of smell.","exKo":"개는 예리한 후각을 가지고 있다."},
        {"id":"d03-09","w":"adamant","ipa":"/ˈædəmənt/","pos":"a","ko":"단호한","syn":["firm","unyielding"],"ex":"She was adamant about leaving the company.","exKo":"그녀는 회사를 떠나는 데 단호했다."},
        {"id":"d03-10","w":"admire","ipa":"/ədˈmaɪər/","pos":"v","ko":"감탄하다, 존경하다","syn":["respect","esteem"],"ex":"I admire her courage and determination.","exKo":"나는 그녀의 용기와 결단력에 감탄한다."},
        {"id":"d03-11","w":"adverse","ipa":"/ˈædvɜːrs/","pos":"a","ko":"불리한","syn":["unfavorable","harmful"],"ex":"The drug can have adverse side effects.","exKo":"그 약은 부정적인 부작용을 일으킬 수 있다."},
        {"id":"d03-12","w":"affirm","ipa":"/əˈfɜːrm/","pos":"v","ko":"확언하다","syn":["confirm","declare"],"ex":"The witness affirmed that the suspect was present.","exKo":"증인은 용의자가 그 자리에 있었다고 확언했다."},
        {"id":"d03-13","w":"afflict","ipa":"/əˈflɪkt/","pos":"v","ko":"괴롭히다","syn":["trouble","distress"],"ex":"Severe drought has afflicted the region for years.","exKo":"극심한 가뭄이 수년간 그 지역을 괴롭혀왔다."},
        {"id":"d03-14","w":"aggravate","ipa":"/ˈæɡrəveɪt/","pos":"v","ko":"악화시키다","syn":["worsen","exacerbate"],"ex":"Stress can aggravate skin problems.","exKo":"스트레스는 피부 문제를 악화시킬 수 있다."},
        {"id":"d03-15","w":"agitate","ipa":"/ˈædʒɪteɪt/","pos":"v","ko":"동요시키다","syn":["disturb","upset"],"ex":"The shocking news agitated the entire community.","exKo":"충격적인 소식이 전체 지역사회를 동요시켰다."},
        {"id":"d03-16","w":"ailment","ipa":"/ˈeɪlmənt/","pos":"n","ko":"(가벼운) 질병","syn":["illness","malady"],"ex":"Herbal teas are often used to treat minor ailments.","exKo":"허브차는 가벼운 질병 치료에 자주 쓰인다."},
        {"id":"d03-17","w":"alienate","ipa":"/ˈeɪliəneɪt/","pos":"v","ko":"소외시키다","syn":["estrange","isolate"],"ex":"His rude behavior alienated his colleagues.","exKo":"그의 무례한 행동은 동료들을 멀어지게 했다."},
        {"id":"d03-18","w":"allegiance","ipa":"/əˈliːdʒəns/","pos":"n","ko":"충성","syn":["loyalty","fidelity"],"ex":"Soldiers swore allegiance to their country.","exKo":"군인들은 조국에 대한 충성을 맹세했다."},
        {"id":"d03-19","w":"aloof","ipa":"/əˈluːf/","pos":"a","ko":"냉담한","syn":["distant","detached"],"ex":"He remained aloof during the entire party.","exKo":"그는 파티 내내 거리를 두고 있었다."},
        {"id":"d03-20","w":"altruistic","ipa":"/ˌæltruˈɪstɪk/","pos":"a","ko":"이타적인","syn":["selfless","benevolent"],"ex":"Her altruistic actions inspired others to help.","exKo":"그녀의 이타적인 행동은 다른 사람들도 돕도록 자극했다."},
        {"id":"d03-21","w":"amend","ipa":"/əˈmend/","pos":"v","ko":"수정하다, 개정하다","syn":["revise","modify"],"ex":"Congress voted to amend the constitution.","exKo":"의회는 헌법을 개정하기 위해 투표했다."},
        {"id":"d03-22","w":"amiable","ipa":"/ˈeɪmiəbəl/","pos":"a","ko":"상냥한","syn":["friendly","affable"],"ex":"Our new neighbor is an amiable old gentleman.","exKo":"우리 새 이웃은 상냥한 노신사이다."},
        {"id":"d03-23","w":"analogous","ipa":"/əˈnæləɡəs/","pos":"a","ko":"유사한","syn":["similar","comparable"],"ex":"The human eye is analogous to a camera.","exKo":"인간의 눈은 카메라와 유사하다."},
        {"id":"d03-24","w":"annihilate","ipa":"/əˈnaɪəleɪt/","pos":"v","ko":"전멸시키다","syn":["destroy","obliterate"],"ex":"The army annihilated the enemy forces.","exKo":"군대는 적군을 전멸시켰다."},
        {"id":"d03-25","w":"apex","ipa":"/ˈeɪpeks/","pos":"n","ko":"정점","syn":["peak","summit"],"ex":"She reached the apex of her career at age 35.","exKo":"그녀는 35세에 경력의 정점에 도달했다."}
      ]
    },
    {
      "day": 4,
      "date": "2026-05-25",
      "category": "vocab",
      "words": [
        {"id":"d04-01","w":"arrogant","ipa":"/ˈærəɡənt/","pos":"a","ko":"거만한","syn":["haughty","conceited"],"ex":"His arrogant attitude annoyed his colleagues.","exKo":"그의 거만한 태도는 동료들을 짜증나게 했다."},
        {"id":"d04-02","w":"astute","ipa":"/əˈstuːt/","pos":"a","ko":"영리한","syn":["shrewd","perceptive"],"ex":"She is an astute investor with a sharp eye for trends.","exKo":"그녀는 트렌드를 보는 눈이 날카로운 영리한 투자자다."},
        {"id":"d04-03","w":"averse","ipa":"/əˈvɜːrs/","pos":"a","ko":"꺼리는","syn":["opposed","reluctant"],"ex":"He is averse to taking risks in business.","exKo":"그는 사업에서 위험을 감수하는 것을 꺼린다."},
        {"id":"d04-04","w":"baffle","ipa":"/ˈbæfəl/","pos":"v","ko":"당황하게 하다","syn":["perplex","confound"],"ex":"The mystery continues to baffle scientists.","exKo":"그 수수께끼는 과학자들을 계속 당황하게 한다."},
        {"id":"d04-05","w":"banish","ipa":"/ˈbænɪʃ/","pos":"v","ko":"추방하다","syn":["expel","exile"],"ex":"The king banished the traitor from the kingdom.","exKo":"왕은 반역자를 왕국에서 추방했다."},
        {"id":"d04-06","w":"barren","ipa":"/ˈbærən/","pos":"a","ko":"황량한, 불모의","syn":["infertile","desolate"],"ex":"Nothing grows on this barren land.","exKo":"이 불모지에서는 아무것도 자라지 않는다."},
        {"id":"d04-07","w":"belittle","ipa":"/bɪˈlɪtəl/","pos":"v","ko":"깎아내리다","syn":["disparage","demean"],"ex":"Don't belittle his efforts; he tried his best.","exKo":"그의 노력을 깎아내리지 마라."},
        {"id":"d04-08","w":"benevolent","ipa":"/bəˈnevələnt/","pos":"a","ko":"자비로운","syn":["kind","charitable"],"ex":"The benevolent donor gave millions to charity.","exKo":"그 자비로운 기부자는 자선단체에 수백만을 기부했다."},
        {"id":"d04-09","w":"blatant","ipa":"/ˈbleɪtənt/","pos":"a","ko":"노골적인","syn":["obvious","flagrant"],"ex":"His blatant lie shocked the courtroom.","exKo":"그의 노골적인 거짓말이 법정을 충격에 빠뜨렸다."},
        {"id":"d04-10","w":"brevity","ipa":"/ˈbrevəti/","pos":"n","ko":"간결함","syn":["conciseness","terseness"],"ex":"The brevity of his speech impressed everyone.","exKo":"그의 연설의 간결함은 모두에게 깊은 인상을 주었다."},
        {"id":"d04-11","w":"candid","ipa":"/ˈkændɪd/","pos":"a","ko":"솔직한","syn":["frank","honest"],"ex":"She gave a candid interview about her career.","exKo":"그녀는 자신의 경력에 대해 솔직한 인터뷰를 했다."},
        {"id":"d04-12","w":"capricious","ipa":"/kəˈprɪʃəs/","pos":"a","ko":"변덕스러운","syn":["fickle","erratic"],"ex":"The weather here is capricious in spring.","exKo":"이곳의 봄 날씨는 변덕스럽다."},
        {"id":"d04-13","w":"censure","ipa":"/ˈsenʃər/","pos":"v","ko":"비난하다, 견책하다","syn":["criticize","rebuke"],"ex":"The senator was censured for his misconduct.","exKo":"그 상원의원은 비행으로 견책당했다."},
        {"id":"d04-14","w":"chronic","ipa":"/ˈkrɒnɪk/","pos":"a","ko":"만성적인","syn":["persistent","long-lasting"],"ex":"He suffers from chronic back pain.","exKo":"그는 만성적인 허리 통증으로 고생하고 있다."},
        {"id":"d04-15","w":"circumvent","ipa":"/ˌsɜːrkəmˈvent/","pos":"v","ko":"우회하다","syn":["bypass","evade"],"ex":"They tried to circumvent the regulations.","exKo":"그들은 규정을 우회하려 했다."},
        {"id":"d04-16","w":"clandestine","ipa":"/klænˈdestɪn/","pos":"a","ko":"비밀의","syn":["secret","covert"],"ex":"They held clandestine meetings at night.","exKo":"그들은 밤에 비밀 회동을 가졌다."},
        {"id":"d04-17","w":"coerce","ipa":"/koʊˈɜːrs/","pos":"v","ko":"강요하다","syn":["force","pressure"],"ex":"The witness was coerced into testifying.","exKo":"그 증인은 증언하도록 강요받았다."},
        {"id":"d04-18","w":"cohesive","ipa":"/koʊˈhiːsɪv/","pos":"a","ko":"결속력 있는","syn":["united","unified"],"ex":"The team became more cohesive after training.","exKo":"그 팀은 훈련 후 더욱 결속력 있어졌다."},
        {"id":"d04-19","w":"commemorate","ipa":"/kəˈmeməreɪt/","pos":"v","ko":"기념하다","syn":["honor","celebrate"],"ex":"The ceremony commemorates fallen soldiers.","exKo":"그 의식은 전사한 병사들을 기념한다."},
        {"id":"d04-20","w":"compatible","ipa":"/kəmˈpætəbəl/","pos":"a","ko":"호환되는","syn":["consistent","harmonious"],"ex":"This software is compatible with most devices.","exKo":"이 소프트웨어는 대부분의 기기와 호환된다."},
        {"id":"d04-21","w":"compromise","ipa":"/ˈkɒmprəmaɪz/","pos":"v","ko":"타협하다","syn":["settle","concede"],"ex":"Both sides had to compromise to reach an agreement.","exKo":"양측은 합의에 이르기 위해 타협해야 했다."},
        {"id":"d04-22","w":"concede","ipa":"/kənˈsiːd/","pos":"v","ko":"인정하다","syn":["admit","acknowledge"],"ex":"He finally conceded that he was wrong.","exKo":"그는 마침내 자신이 틀렸음을 인정했다."},
        {"id":"d04-23","w":"condense","ipa":"/kənˈdens/","pos":"v","ko":"응축하다","syn":["compress","abridge"],"ex":"Please condense the report into one page.","exKo":"보고서를 한 페이지로 압축해 주세요."},
        {"id":"d04-24","w":"confer","ipa":"/kənˈfɜːr/","pos":"v","ko":"협의하다, 수여하다","syn":["consult","bestow"],"ex":"The doctors conferred about the patient's treatment.","exKo":"의사들은 환자의 치료에 대해 협의했다."},
        {"id":"d04-25","w":"confront","ipa":"/kənˈfrʌnt/","pos":"v","ko":"직면하다","syn":["face","encounter"],"ex":"She decided to confront her fears head-on.","exKo":"그녀는 자신의 두려움에 정면으로 맞서기로 결심했다."}
      ]
    },
    {
      "day": 5,
      "date": "2026-05-26",
      "category": "vocab",
      "words": [
        {"id":"d05-01","w":"construe","ipa":"/kənˈstruː/","pos":"v","ko":"해석하다","syn":["interpret","infer"],"ex":"His silence was construed as agreement.","exKo":"그의 침묵은 동의로 해석되었다."},
        {"id":"d05-02","w":"courteous","ipa":"/ˈkɜːrtiəs/","pos":"a","ko":"정중한","syn":["polite","civil"],"ex":"The hotel staff was extremely courteous.","exKo":"그 호텔 직원은 매우 정중했다."},
        {"id":"d05-03","w":"cumbersome","ipa":"/ˈkʌmbərsəm/","pos":"a","ko":"거추장스러운","syn":["bulky","unwieldy"],"ex":"The old equipment was heavy and cumbersome.","exKo":"그 낡은 장비는 무겁고 거추장스러웠다."},
        {"id":"d05-04","w":"curtail","ipa":"/kɜːrˈteɪl/","pos":"v","ko":"축소하다","syn":["reduce","shorten"],"ex":"The company curtailed spending due to losses.","exKo":"그 회사는 손실로 인해 지출을 축소했다."},
        {"id":"d05-05","w":"decipher","ipa":"/dɪˈsaɪfər/","pos":"v","ko":"해독하다","syn":["decode","interpret"],"ex":"It took hours to decipher the ancient text.","exKo":"그 고대 문서를 해독하는 데 몇 시간이 걸렸다."},
        {"id":"d05-06","w":"defer","ipa":"/dɪˈfɜːr/","pos":"v","ko":"연기하다","syn":["postpone","delay"],"ex":"We decided to defer the meeting until next week.","exKo":"우리는 회의를 다음 주로 연기하기로 했다."},
        {"id":"d05-07","w":"defiant","ipa":"/dɪˈfaɪənt/","pos":"a","ko":"반항적인","syn":["rebellious","resistant"],"ex":"The defiant student refused to obey the rules.","exKo":"그 반항적인 학생은 규칙을 따르기를 거부했다."},
        {"id":"d05-08","w":"deluge","ipa":"/ˈdeljuːdʒ/","pos":"n","ko":"폭우, 쇄도","syn":["flood","downpour"],"ex":"The office received a deluge of complaints.","exKo":"그 사무실에는 불만이 쇄도했다."},
        {"id":"d05-09","w":"demanding","ipa":"/dɪˈmændɪŋ/","pos":"a","ko":"부담이 큰","syn":["challenging","exacting"],"ex":"Being a parent is a demanding job.","exKo":"부모가 되는 것은 부담이 큰 일이다."},
        {"id":"d05-10","w":"denote","ipa":"/dɪˈnoʊt/","pos":"v","ko":"나타내다","syn":["indicate","signify"],"ex":"A red light denotes danger.","exKo":"빨간 불빛은 위험을 나타낸다."},
        {"id":"d05-11","w":"deplore","ipa":"/dɪˈplɔːr/","pos":"v","ko":"개탄하다","syn":["lament","regret"],"ex":"Many citizens deplore the rise in crime.","exKo":"많은 시민들이 범죄 증가를 개탄한다."},
        {"id":"d05-12","w":"derive","ipa":"/dɪˈraɪv/","pos":"v","ko":"유래하다, 얻다","syn":["obtain","originate"],"ex":"She derives great satisfaction from her work.","exKo":"그녀는 자신의 일에서 큰 만족을 얻는다."},
        {"id":"d05-13","w":"detain","ipa":"/dɪˈteɪn/","pos":"v","ko":"구금하다","syn":["hold","retain"],"ex":"The police detained him for questioning.","exKo":"경찰은 그를 심문하기 위해 구금했다."},
        {"id":"d05-14","w":"deter","ipa":"/dɪˈtɜːr/","pos":"v","ko":"단념시키다, 저지하다","syn":["discourage","prevent"],"ex":"Heavy penalties may deter crime.","exKo":"무거운 형벌은 범죄를 저지할 수 있다."},
        {"id":"d05-15","w":"detrimental","ipa":"/ˌdetrɪˈmentəl/","pos":"a","ko":"해로운","syn":["harmful","damaging"],"ex":"Smoking is detrimental to your health.","exKo":"흡연은 건강에 해롭다."},
        {"id":"d05-16","w":"deviate","ipa":"/ˈdiːvieɪt/","pos":"v","ko":"벗어나다","syn":["depart","stray"],"ex":"Don't deviate from the original plan.","exKo":"원래 계획에서 벗어나지 마라."},
        {"id":"d05-17","w":"dexterity","ipa":"/dekˈsterəti/","pos":"n","ko":"손재주","syn":["skill","agility"],"ex":"Surgeons need great manual dexterity.","exKo":"외과의사는 뛰어난 손재주가 필요하다."},
        {"id":"d05-18","w":"dilute","ipa":"/daɪˈluːt/","pos":"v","ko":"희석하다","syn":["weaken","thin"],"ex":"You should dilute the juice with water.","exKo":"주스를 물로 희석해야 한다."},
        {"id":"d05-19","w":"dispatch","ipa":"/dɪˈspætʃ/","pos":"v","ko":"파견하다","syn":["send","forward"],"ex":"The company dispatched a team to investigate.","exKo":"그 회사는 조사하기 위해 팀을 파견했다."},
        {"id":"d05-20","w":"disperse","ipa":"/dɪˈspɜːrs/","pos":"v","ko":"흩어지다","syn":["scatter","distribute"],"ex":"The crowd dispersed after the speech.","exKo":"군중은 연설 후 흩어졌다."},
        {"id":"d05-21","w":"disrupt","ipa":"/dɪsˈrʌpt/","pos":"v","ko":"방해하다","syn":["disturb","interrupt"],"ex":"The protest disrupted traffic for hours.","exKo":"시위는 몇 시간 동안 교통을 방해했다."},
        {"id":"d05-22","w":"divert","ipa":"/daɪˈvɜːrt/","pos":"v","ko":"우회시키다","syn":["redirect","deflect"],"ex":"The river was diverted to prevent floods.","exKo":"홍수를 막기 위해 강물이 우회되었다."},
        {"id":"d05-23","w":"dormant","ipa":"/ˈdɔːrmənt/","pos":"a","ko":"휴면 중인","syn":["inactive","latent"],"ex":"The volcano has been dormant for centuries.","exKo":"그 화산은 수세기 동안 휴면 상태이다."},
        {"id":"d05-24","w":"drastic","ipa":"/ˈdræstɪk/","pos":"a","ko":"과감한, 극단적인","syn":["extreme","severe"],"ex":"Drastic measures are needed to solve this.","exKo":"이것을 해결하려면 과감한 조치가 필요하다."},
        {"id":"d05-25","w":"dubious","ipa":"/ˈduːbiəs/","pos":"a","ko":"의심스러운","syn":["doubtful","questionable"],"ex":"I'm dubious about his real intentions.","exKo":"나는 그의 진짜 의도가 의심스럽다."}
      ]
    },
    {
      "day": 6,
      "date": "2026-05-27",
      "category": "vocab",
      "words": [
        {"id":"d06-01","w":"discrepancy","ipa":"/dɪˈskrepənsi/","pos":"n","ko":"불일치, 차이","syn":["inconsistency","disparity"],"ex":"There is a discrepancy between his story and the facts.","exKo":"그의 이야기와 사실 사이에 불일치가 있다."},
        {"id":"d06-02","w":"discriminate","ipa":"/dɪˈskrɪmɪneɪt/","pos":"v","ko":"차별하다, 구별하다","syn":["differentiate","distinguish"],"ex":"It is illegal to discriminate against people based on race.","exKo":"인종에 따라 사람을 차별하는 것은 불법이다."},
        {"id":"d06-03","w":"disdain","ipa":"/dɪsˈdeɪn/","pos":"n","ko":"경멸","syn":["contempt","scorn"],"ex":"She looked at him with disdain.","exKo":"그녀는 경멸의 눈빛으로 그를 바라보았다."},
        {"id":"d06-04","w":"disguise","ipa":"/dɪsˈɡaɪz/","pos":"v","ko":"변장하다, 위장하다","syn":["conceal","mask"],"ex":"The spy disguised himself as a waiter.","exKo":"그 스파이는 웨이터로 변장했다."},
        {"id":"d06-05","w":"dismiss","ipa":"/dɪsˈmɪs/","pos":"v","ko":"해고하다, 일축하다","syn":["reject","discharge"],"ex":"The manager dismissed the proposal without discussion.","exKo":"매니저는 토론 없이 그 제안을 일축했다."},
        {"id":"d06-06","w":"dispense","ipa":"/dɪˈspens/","pos":"v","ko":"분배하다","syn":["distribute","administer"],"ex":"The machine dispenses hot coffee.","exKo":"그 기계는 뜨거운 커피를 분배한다."},
        {"id":"d06-07","w":"dispose","ipa":"/dɪˈspoʊz/","pos":"v","ko":"처리하다","syn":["discard","remove"],"ex":"Please dispose of the trash properly.","exKo":"쓰레기를 적절히 처리해 주세요."},
        {"id":"d06-08","w":"dissolve","ipa":"/dɪˈzɒlv/","pos":"v","ko":"녹이다, 해산하다","syn":["melt","disband"],"ex":"Salt dissolves easily in water.","exKo":"소금은 물에 쉽게 녹는다."},
        {"id":"d06-09","w":"distort","ipa":"/dɪˈstɔːrt/","pos":"v","ko":"왜곡하다","syn":["twist","misrepresent"],"ex":"The media distorted the facts of the case.","exKo":"언론은 그 사건의 사실을 왜곡했다."},
        {"id":"d06-10","w":"divulge","ipa":"/daɪˈvʌldʒ/","pos":"v","ko":"누설하다","syn":["disclose","reveal"],"ex":"He refused to divulge any details about the project.","exKo":"그는 프로젝트에 대한 어떤 세부사항도 누설하기를 거부했다."},
        {"id":"d06-11","w":"dwindle","ipa":"/ˈdwɪndəl/","pos":"v","ko":"점점 줄어들다","syn":["shrink","decrease"],"ex":"Our supplies are beginning to dwindle.","exKo":"우리의 보급품이 점점 줄어들기 시작했다."},
        {"id":"d06-12","w":"eccentric","ipa":"/ɪkˈsentrɪk/","pos":"a","ko":"별난, 기이한","syn":["peculiar","odd"],"ex":"The eccentric professor always wore mismatched socks.","exKo":"그 별난 교수는 항상 짝짝이 양말을 신었다."},
        {"id":"d06-13","w":"edible","ipa":"/ˈedəbəl/","pos":"a","ko":"먹을 수 있는","syn":["eatable","palatable"],"ex":"Not all mushrooms in the forest are edible.","exKo":"숲의 모든 버섯이 먹을 수 있는 것은 아니다."},
        {"id":"d06-14","w":"eloquent","ipa":"/ˈeləkwənt/","pos":"a","ko":"유창한","syn":["articulate","fluent"],"ex":"She gave an eloquent speech about freedom.","exKo":"그녀는 자유에 대한 유창한 연설을 했다."},
        {"id":"d06-15","w":"embark","ipa":"/ɪmˈbɑːrk/","pos":"v","ko":"시작하다, 승선하다","syn":["begin","commence"],"ex":"We are about to embark on a new project.","exKo":"우리는 곧 새 프로젝트를 시작할 것이다."},
        {"id":"d06-16","w":"embrace","ipa":"/ɪmˈbreɪs/","pos":"v","ko":"포옹하다, 받아들이다","syn":["hug","accept"],"ex":"The company embraced the new technology quickly.","exKo":"그 회사는 새 기술을 빠르게 받아들였다."},
        {"id":"d06-17","w":"emerge","ipa":"/ɪˈmɜːrdʒ/","pos":"v","ko":"나타나다","syn":["appear","surface"],"ex":"New evidence emerged during the trial.","exKo":"재판 중에 새로운 증거가 드러났다."},
        {"id":"d06-18","w":"eminent","ipa":"/ˈemɪnənt/","pos":"a","ko":"저명한","syn":["distinguished","renowned"],"ex":"She is an eminent scientist in her field.","exKo":"그녀는 자기 분야의 저명한 과학자이다."},
        {"id":"d06-19","w":"empathy","ipa":"/ˈempəθi/","pos":"n","ko":"공감","syn":["compassion","understanding"],"ex":"A good leader shows empathy toward employees.","exKo":"훌륭한 지도자는 직원들에게 공감을 보인다."},
        {"id":"d06-20","w":"empirical","ipa":"/ɪmˈpɪrɪkəl/","pos":"a","ko":"경험적인, 실증적인","syn":["observed","experimental"],"ex":"The theory is based on empirical evidence.","exKo":"그 이론은 실증적 증거에 기반하고 있다."},
        {"id":"d06-21","w":"emulate","ipa":"/ˈemjəleɪt/","pos":"v","ko":"모방하다, 본받다","syn":["imitate","mimic"],"ex":"Young athletes often emulate their heroes.","exKo":"어린 운동선수들은 종종 자신의 영웅을 본받는다."},
        {"id":"d06-22","w":"encompass","ipa":"/ɪnˈkʌmpəs/","pos":"v","ko":"포함하다","syn":["include","surround"],"ex":"The course encompasses all aspects of design.","exKo":"그 강좌는 디자인의 모든 측면을 포함한다."},
        {"id":"d06-23","w":"endeavor","ipa":"/ɪnˈdevər/","pos":"v","ko":"노력하다","syn":["strive","attempt"],"ex":"We endeavor to provide the best service.","exKo":"우리는 최고의 서비스를 제공하기 위해 노력한다."},
        {"id":"d06-24","w":"endorse","ipa":"/ɪnˈdɔːrs/","pos":"v","ko":"지지하다, 보증하다","syn":["support","approve"],"ex":"The senator endorsed the new education bill.","exKo":"그 상원의원은 새 교육 법안을 지지했다."},
        {"id":"d06-25","w":"enduring","ipa":"/ɪnˈdjʊrɪŋ/","pos":"a","ko":"지속되는","syn":["lasting","permanent"],"ex":"Their friendship has been enduring through hard times.","exKo":"그들의 우정은 힘든 시기를 지나 지속되어 왔다."}
      ]
    },
    {
      "day": 101,
      "date": "2026-05-26",
      "category": "listening",
      "label": "청해 Day 1",
      "words": [
        {"id":"l01-01","w":"career","ipa":"/kəˈrɪr/","pos":"n","ko":"직업, 경력","syn":["profession","occupation"],"note":"강세: 둘째 음절 (ca-REER) — 한국어 '커리어'와 달리 뒤에 강세!","ex":"She built a successful career in engineering.","exKo":"그녀는 공학 분야에서 성공적인 경력을 쌓았다."},
        {"id":"l01-02","w":"courier","ipa":"/ˈkʊriər/","pos":"n","ko":"택배원, 운반자","syn":["messenger","carrier"],"note":"강세: 첫째 음절 (COU-ri-er) — career와 강세 정반대! 청해 단골 함정","ex":"The package was delivered by a courier this morning.","exKo":"그 소포는 오늘 아침 택배원이 배달했다."},
        {"id":"l01-03","w":"give one's regards (to)","ipa":"/ɡɪv … rɪˈɡɑːrdz/","pos":"phrase","ko":"~에게 안부를 전하다","syn":["send greetings"],"ex":"Give my regards to your family.","exKo":"가족분들께 안부 전해 주세요."},
        {"id":"l01-04","w":"put (O) through to","ipa":"/pʊt … θruː tuː/","pos":"phrasal","ko":"(전화를) ~에게 연결해 주다","syn":["connect","transfer"],"note":"연음 주의: 'put-it-through-to' → '푸딧스루투'","ex":"Could you put me through to Mr. Kim, please?","exKo":"김 선생님께 연결해 주시겠어요?"},
        {"id":"l01-05","w":"come up","ipa":"/kʌm ʌp/","pos":"phrasal","ko":"(일이) 생기다, 발생하다","syn":["arise","happen"],"note":"연음: 'ca-MUP'으로 들림","ex":"Something came up, so I have to cancel.","exKo":"일이 생겨서 취소해야 해요."},
        {"id":"l01-06","w":"pass up","ipa":"/pæs ʌp/","pos":"phrasal","ko":"(기회를) 거절하다, 놓치다","syn":["decline","forgo"],"note":"연음: 'pa-SUP'으로 들림","ex":"Don't pass up this great opportunity.","exKo":"이 좋은 기회를 놓치지 마라."},
        {"id":"l01-07","w":"think through","ipa":"/θɪŋk θruː/","pos":"phrasal","ko":"충분히 숙고하다","syn":["consider","ponder"],"ex":"I need to think this through before deciding.","exKo":"결정하기 전에 이것을 충분히 생각해야 해."},
        {"id":"l01-08","w":"cover letter","ipa":"/ˈkʌvər ˌletər/","pos":"n","ko":"자기소개서","syn":["application letter"],"note":"강세: COV-er LET-ter (두 단어 모두 첫음절)","ex":"Please attach your cover letter with your resume.","exKo":"이력서와 함께 자기소개서를 첨부해 주세요."},
        {"id":"l01-09","w":"résumé","ipa":"/ˈrezʊmeɪ/","pos":"n","ko":"이력서 (미국식)","syn":["CV"],"note":"명사(이력서): /ˈrezʊmeɪ/ '레즈메이' / 동사(재개하다): /rɪˈzuːm/ '리줌' — 강세 완전 다름!","ex":"I sent my resume to three companies.","exKo":"이력서를 세 회사에 보냈다."},
        {"id":"l01-10","w":"look over","ipa":"/lʊk ˈoʊvər/","pos":"phrasal","ko":"훑어보다, 검토하다","syn":["review","examine"],"note":"연음: 'loo-KO-ver'","ex":"Could you look over my essay before I submit it?","exKo":"제출하기 전에 제 에세이를 검토해 주실래요?"},
        {"id":"l01-11","w":"for any errors","ipa":"/fər ˈeni ˈerərz/","pos":"phrase","ko":"오류가 있는지","syn":["for mistakes"],"note":"청해 빈출 조합: 'look it over for any errors'","ex":"Please check the document for any errors.","exKo":"문서에 오류가 있는지 확인해 주세요."},
        {"id":"l01-12","w":"not that I'm aware of","ipa":"/nɒt ðæt aɪm əˈwer əv/","pos":"phrase","ko":"제가 알기로는 아닙니다","syn":["not to my knowledge"],"note":"연음: '낫댓아임어웨어러브' — 청해 빈출 답변","ex":"\"Is there a problem?\" \"Not that I'm aware of.\"","exKo":"\"문제가 있나요?\" \"제가 알기로는 없어요.\""},
        {"id":"l01-13","w":"look through","ipa":"/lʊk θruː/","pos":"phrasal","ko":"살펴보다, 뒤지다","syn":["examine","peruse"],"note":"look over vs look through: over는 가볍게, through는 자세히","ex":"I looked through all the files but couldn't find it.","exKo":"모든 파일을 살펴봤지만 찾을 수 없었다."},
        {"id":"l01-14","w":"Have you heard ~ yet?","ipa":"/hæv juː hɜːrd … jet/","pos":"phrase","ko":"~ 들었어요?","syn":["Did you hear about ~?"],"note":"연음: 'ha-vyu-HEARD'; 끝의 'yet'은 약하게","ex":"Have you heard the news yet?","exKo":"그 소식 들었어?"}
      ]
    }
  ]
}
